databricksPackageVTn/__init__.py
databricksPackageVTn/module1.py
databricksPackageVTn/module2.py
databricksPackageVTn-0.7.dist-info/METADATA
databricksPackageVTn-0.7.dist-info/WHEEL
databricksPackageVTn-0.7.dist-info/top_level.txt
databricksPackageVTn-0.7.dist-info/RECORD
